{
    "key": "group_5f248e7cecff7",
    "title": "Low-Code Guide",
    "fields": [
        {
            "key": "field_5f983df74a8b8",
            "label": "Hero",
            "name": "",
            "type": "accordion",
            "instructions": "",
            "required": 0,
            "conditional_logic": 0,
            "wrapper": {
                "width": "",
                "class": "",
                "id": ""
            },
            "open": 0,
            "multi_expand": 0,
            "endpoint": 0
        },
        {
            "key": "field_5f983e044a8b9",
            "label": "Background",
            "name": "lcg_hero_background",
            "type": "image",
            "instructions": "",
            "required": 0,
            "conditional_logic": 0,
            "wrapper": {
                "width": "",
                "class": "",
                "id": ""
            },
            "return_format": "array",
            "preview_size": "post-thumbnail",
            "library": "all",
            "min_width": "",
            "min_height": "",
            "min_size": "",
            "max_width": "",
            "max_height": "",
            "max_size": "",
            "mime_types": "",
            "translations": "copy_once"
        },
        {
            "key": "field_5f983e1c4a8ba",
            "label": "Heading",
            "name": "lcg_hero_heading",
            "type": "text",
            "instructions": "",
            "required": 0,
            "conditional_logic": 0,
            "wrapper": {
                "width": "",
                "class": "",
                "id": ""
            },
            "default_value": "Raise your low-code expectations",
            "placeholder": "Raise your low-code expectations",
            "prepend": "",
            "append": "",
            "maxlength": "",
            "translations": "translate"
        },
        {
            "key": "field_5f983e624a8bb",
            "label": "Subheading",
            "name": "lcg_hero_subheading",
            "type": "textarea",
            "instructions": "",
            "required": 0,
            "conditional_logic": 0,
            "wrapper": {
                "width": "",
                "class": "",
                "id": ""
            },
            "default_value": "This isn’t just about drag-and-drop. It’s about making something that transforms the enterprise app landscape.",
            "placeholder": "This isn’t just about drag-and-drop. It’s about making something that transforms the enterprise app landscape.",
            "maxlength": "",
            "rows": "",
            "new_lines": "",
            "translations": "translate"
        },
        {
            "key": "field_5f248e7d1235f",
            "label": "Low Code Development",
            "name": "",
            "type": "accordion",
            "instructions": "",
            "required": 0,
            "conditional_logic": 0,
            "wrapper": {
                "width": "",
                "class": "",
                "id": ""
            },
            "open": 0,
            "multi_expand": 0,
            "endpoint": 0
        },
        {
            "key": "field_5f2812f7744f5",
            "label": "Low Code Development Group",
            "name": "low_code_development_group",
            "type": "group",
            "instructions": "",
            "required": 0,
            "conditional_logic": 0,
            "wrapper": {
                "width": "",
                "class": "",
                "id": ""
            },
            "layout": "block",
            "sub_fields": [
                {
                    "key": "field_5f248e7d1236c",
                    "label": "Development Heading",
                    "name": "development_heading",
                    "type": "text",
                    "instructions": "The big heading text for this section",
                    "required": 1,
                    "conditional_logic": [
                        [
                            {
                                "field": "field_5f248e7d12366",
                                "operator": "==",
                                "value": "1"
                            }
                        ]
                    ],
                    "wrapper": {
                        "width": "",
                        "class": "",
                        "id": ""
                    },
                    "default_value": "",
                    "placeholder": "",
                    "prepend": "",
                    "append": "",
                    "maxlength": "",
                    "translations": "translate"
                },
                {
                    "key": "field_5f248e7d12372",
                    "label": "Development Body Text",
                    "name": "development_body_text",
                    "type": "wysiwyg",
                    "instructions": "Body text for the Development section",
                    "required": 0,
                    "conditional_logic": [
                        [
                            {
                                "field": "field_5f248e7d12366",
                                "operator": "==",
                                "value": "1"
                            }
                        ]
                    ],
                    "wrapper": {
                        "width": "",
                        "class": "",
                        "id": ""
                    },
                    "default_value": "",
                    "tabs": "all",
                    "toolbar": "full",
                    "media_upload": 1,
                    "delay": 0,
                    "translations": "translate"
                },
                {
                    "key": "field_5f249090c9bbf",
                    "label": "Development Quote by",
                    "name": "development_quote_by",
                    "type": "text",
                    "instructions": "Kicker style blue heading",
                    "required": 0,
                    "conditional_logic": [
                        [
                            {
                                "field": "field_5f248e7d12366",
                                "operator": "==",
                                "value": "1"
                            }
                        ]
                    ],
                    "wrapper": {
                        "width": "",
                        "class": "",
                        "id": ""
                    },
                    "default_value": "",
                    "placeholder": "",
                    "prepend": "",
                    "append": "",
                    "maxlength": "",
                    "translations": "translate"
                },
                {
                    "key": "field_5f249050c9bbe",
                    "label": "Development Quote",
                    "name": "development_quote",
                    "type": "textarea",
                    "instructions": "Quote to display in the right column",
                    "required": 0,
                    "conditional_logic": [
                        [
                            {
                                "field": "field_5f248e7d12366",
                                "operator": "==",
                                "value": "1"
                            }
                        ]
                    ],
                    "wrapper": {
                        "width": "",
                        "class": "",
                        "id": ""
                    },
                    "default_value": "",
                    "placeholder": "",
                    "maxlength": "",
                    "rows": "",
                    "new_lines": "",
                    "translations": "translate"
                },
                {
                    "key": "field_5f248e7d12378",
                    "label": "Development Cards",
                    "name": "development_cards",
                    "type": "clone",
                    "instructions": "You may add 1 or more values to this section.",
                    "required": 1,
                    "conditional_logic": [
                        [
                            {
                                "field": "field_5f248e7d12366",
                                "operator": "==",
                                "value": "1"
                            }
                        ]
                    ],
                    "wrapper": {
                        "width": "",
                        "class": "",
                        "id": ""
                    },
                    "clone": [
                        "group_5d36373248b73"
                    ],
                    "display": "seamless",
                    "layout": "block",
                    "prefix_label": 0,
                    "prefix_name": 0
                },
                {
                    "key": "field_5f24a35a51d34",
                    "label": "Development Benefits",
                    "name": "development_benefits",
                    "type": "repeater",
                    "instructions": "",
                    "required": 0,
                    "conditional_logic": [
                        [
                            {
                                "field": "field_5f248e7d12366",
                                "operator": "==",
                                "value": "1"
                            }
                        ]
                    ],
                    "wrapper": {
                        "width": "",
                        "class": "",
                        "id": ""
                    },
                    "collapsed": "",
                    "min": 0,
                    "max": 0,
                    "layout": "row",
                    "button_label": "",
                    "sub_fields": [
                        {
                            "key": "field_5f24a35a51d37",
                            "label": "Icon",
                            "name": "benefits_value_icon",
                            "type": "image",
                            "instructions": "",
                            "required": 1,
                            "conditional_logic": 0,
                            "wrapper": {
                                "width": "",
                                "class": "",
                                "id": ""
                            },
                            "return_format": "array",
                            "preview_size": "post-thumbnail",
                            "library": "all",
                            "min_width": "",
                            "min_height": "",
                            "min_size": "",
                            "max_width": "",
                            "max_height": "",
                            "max_size": "",
                            "mime_types": "",
                            "translations": "copy_once"
                        },
                        {
                            "key": "field_5f24a35a51d35",
                            "label": "Heading",
                            "name": "benefits_value_heading",
                            "type": "text",
                            "instructions": "",
                            "required": 1,
                            "conditional_logic": [
                                [
                                    {
                                        "field": "field_5f248e7d12366",
                                        "operator": "==",
                                        "value": "1"
                                    }
                                ]
                            ],
                            "wrapper": {
                                "width": "",
                                "class": "",
                                "id": ""
                            },
                            "default_value": "",
                            "placeholder": "",
                            "prepend": "",
                            "append": "",
                            "maxlength": "",
                            "translations": "translate"
                        },
                        {
                            "key": "field_5f24a35a51d36",
                            "label": "Description",
                            "name": "benefits_value_text",
                            "type": "repeater",
                            "instructions": "",
                            "required": 0,
                            "conditional_logic": 0,
                            "wrapper": {
                                "width": "",
                                "class": "",
                                "id": ""
                            },
                            "collapsed": "",
                            "min": 0,
                            "max": 0,
                            "layout": "row",
                            "button_label": "",
                            "sub_fields": [
                                {
                                    "key": "field_5f24a40751d39",
                                    "label": "Benefits Value Body Text",
                                    "name": "benefits_value_body_text",
                                    "type": "textarea",
                                    "instructions": "",
                                    "required": 0,
                                    "conditional_logic": 0,
                                    "wrapper": {
                                        "width": "",
                                        "class": "",
                                        "id": ""
                                    },
                                    "default_value": "",
                                    "placeholder": "",
                                    "maxlength": "",
                                    "rows": "",
                                    "new_lines": "",
                                    "translations": "translate"
                                }
                            ]
                        }
                    ]
                }
            ]
        },
        {
            "key": "field_5f272c2c8e538",
            "label": "Low Code Manifesto",
            "name": "",
            "type": "accordion",
            "instructions": "",
            "required": 0,
            "conditional_logic": 0,
            "wrapper": {
                "width": "",
                "class": "",
                "id": ""
            },
            "open": 0,
            "multi_expand": 0,
            "endpoint": 0
        },
        {
            "key": "field_5f2730e6bb21c",
            "label": "Heading",
            "name": "lcg_manifesto_heading",
            "type": "text",
            "instructions": "",
            "required": 0,
            "conditional_logic": 0,
            "wrapper": {
                "width": "",
                "class": "",
                "id": ""
            },
            "default_value": "The Low-Code Manifesto",
            "placeholder": "The Low-Code Manifesto",
            "prepend": "",
            "append": "",
            "maxlength": "",
            "translations": "translate"
        },
        {
            "key": "field_5f2734d99faaf",
            "label": "Subheading",
            "name": "lcg_manifesto_subheading",
            "type": "textarea",
            "instructions": "",
            "required": 0,
            "conditional_logic": 0,
            "wrapper": {
                "width": "",
                "class": "",
                "id": ""
            },
            "default_value": "Low-code solves the fundamental disconnect between what business needs and what software was delivered. But like any technology, companies need to use it correctly to get value out of it. So, we defined the following 9 Principles of Low-Code Application Development to maximize business impact.",
            "placeholder": "Low-code solves the fundamental disconnect between what business needs and what software was delivered. But like any technology, companies need to use it correctly to get value out of it. So, we defined the following 9 Principles of Low-Code Application Development to maximize business impact.",
            "maxlength": "",
            "rows": "",
            "new_lines": "",
            "translations": "translate"
        },
        {
            "key": "field_5f2738719fab0",
            "label": "Principles Heading",
            "name": "lcg_principles_heading",
            "type": "text",
            "instructions": "",
            "required": 0,
            "conditional_logic": 0,
            "wrapper": {
                "width": "",
                "class": "",
                "id": ""
            },
            "default_value": "The 9 principles of low-code development",
            "placeholder": "The 9 principles of low-code development",
            "prepend": "",
            "append": "",
            "maxlength": "",
            "translations": "translate"
        },
        {
            "key": "field_5f27396cbe039",
            "label": "Principles Cards",
            "name": "lcg_manifesto_cards",
            "type": "repeater",
            "instructions": "",
            "required": 0,
            "conditional_logic": 0,
            "wrapper": {
                "width": "",
                "class": "",
                "id": ""
            },
            "collapsed": "field_5f9859ba63a4d",
            "min": 0,
            "max": 0,
            "layout": "table",
            "button_label": "Add Principle",
            "sub_fields": [
                {
                    "key": "field_5f9859af63a4c",
                    "label": "Icon",
                    "name": "icon",
                    "type": "image",
                    "instructions": "",
                    "required": 0,
                    "conditional_logic": 0,
                    "wrapper": {
                        "width": "",
                        "class": "",
                        "id": ""
                    },
                    "return_format": "array",
                    "preview_size": "post-thumbnail",
                    "library": "all",
                    "min_width": "",
                    "min_height": "",
                    "min_size": "",
                    "max_width": "",
                    "max_height": "",
                    "max_size": "",
                    "mime_types": "",
                    "translations": "copy_once"
                },
                {
                    "key": "field_5f9859ba63a4d",
                    "label": "Text",
                    "name": "text",
                    "type": "text",
                    "instructions": "",
                    "required": 0,
                    "conditional_logic": 0,
                    "wrapper": {
                        "width": "",
                        "class": "",
                        "id": ""
                    },
                    "default_value": "",
                    "placeholder": "",
                    "prepend": "",
                    "append": "",
                    "maxlength": "",
                    "translations": "translate"
                }
            ]
        },
        {
            "key": "field_5f2751f0e8925",
            "label": "Low Code Manifesto Link",
            "name": "lcg_manifesto_cta",
            "type": "link",
            "instructions": "",
            "required": 0,
            "conditional_logic": 0,
            "wrapper": {
                "width": "",
                "class": "",
                "id": ""
            },
            "return_format": "array",
            "translations": "copy_once"
        },
        {
            "key": "field_5f2760aac38ea",
            "label": "Magic Quadrant",
            "name": "",
            "type": "accordion",
            "instructions": "",
            "required": 0,
            "conditional_logic": 0,
            "wrapper": {
                "width": "",
                "class": "",
                "id": ""
            },
            "open": 0,
            "multi_expand": 0,
            "endpoint": 0
        },
        {
            "key": "field_5f27a358677e0",
            "label": "Magic Quadrant Group",
            "name": "magic_quadrant_group",
            "type": "group",
            "instructions": "",
            "required": 0,
            "conditional_logic": 0,
            "wrapper": {
                "width": "",
                "class": "",
                "id": ""
            },
            "layout": "block",
            "sub_fields": [
                {
                    "key": "field_5f27a45e8cdd1",
                    "label": "Magic Quadrant Background",
                    "name": "magic_quadrant_background",
                    "type": "clone",
                    "instructions": "",
                    "required": 0,
                    "conditional_logic": 0,
                    "wrapper": {
                        "width": "",
                        "class": "",
                        "id": ""
                    },
                    "clone": [
                        "field_5dd584131c52a"
                    ],
                    "display": "seamless",
                    "layout": "block",
                    "prefix_label": 0,
                    "prefix_name": 0
                },
                {
                    "key": "field_5f27ebd984ee5",
                    "label": "Magic Quadrant Heading",
                    "name": "magic_quadrant_heading",
                    "type": "clone",
                    "instructions": "",
                    "required": 0,
                    "conditional_logic": 0,
                    "wrapper": {
                        "width": "",
                        "class": "",
                        "id": ""
                    },
                    "clone": [
                        "group_5d8264ced51f7"
                    ],
                    "display": "seamless",
                    "layout": "block",
                    "prefix_label": 0,
                    "prefix_name": 0
                },
                {
                    "key": "field_5f27f1609675d",
                    "label": "Magic Quadrant Image",
                    "name": "magic_quadrant_image",
                    "type": "clone",
                    "instructions": "",
                    "required": 0,
                    "conditional_logic": 0,
                    "wrapper": {
                        "width": "",
                        "class": "",
                        "id": ""
                    },
                    "clone": [
                        "field_5e16330bf270e"
                    ],
                    "display": "seamless",
                    "layout": "block",
                    "prefix_label": 0,
                    "prefix_name": 0
                },
                {
                    "key": "field_5f2c27177859c",
                    "label": "CTA",
                    "name": "magic_quadrant_cta",
                    "type": "link",
                    "instructions": "",
                    "required": 0,
                    "conditional_logic": 0,
                    "wrapper": {
                        "width": "",
                        "class": "",
                        "id": ""
                    },
                    "return_format": "array",
                    "translations": "copy_once"
                }
            ]
        },
        {
            "key": "field_5f27613f06222",
            "label": "Build on Low Code",
            "name": "",
            "type": "accordion",
            "instructions": "",
            "required": 0,
            "conditional_logic": 0,
            "wrapper": {
                "width": "",
                "class": "",
                "id": ""
            },
            "open": 0,
            "multi_expand": 0,
            "endpoint": 0
        },
        {
            "key": "field_5f27a341677df",
            "label": "Build on Low Code Group",
            "name": "build_on_low_code_group",
            "type": "group",
            "instructions": "",
            "required": 0,
            "conditional_logic": 0,
            "wrapper": {
                "width": "",
                "class": "",
                "id": ""
            },
            "layout": "block",
            "sub_fields": [
                {
                    "key": "field_5f7e2794ca848",
                    "label": "Heading",
                    "name": "heading",
                    "type": "text",
                    "instructions": "",
                    "required": 0,
                    "conditional_logic": 0,
                    "wrapper": {
                        "width": "",
                        "class": "",
                        "id": ""
                    },
                    "default_value": "",
                    "placeholder": "",
                    "prepend": "",
                    "append": "",
                    "maxlength": "",
                    "translations": "translate"
                },
                {
                    "key": "field_5f7e2798ca849",
                    "label": "Subheading",
                    "name": "subheading",
                    "type": "textarea",
                    "instructions": "",
                    "required": 0,
                    "conditional_logic": 0,
                    "wrapper": {
                        "width": "",
                        "class": "",
                        "id": ""
                    },
                    "default_value": "",
                    "placeholder": "",
                    "maxlength": "",
                    "rows": "",
                    "new_lines": "",
                    "translations": "translate"
                },
                {
                    "key": "field_5f7e27a2ca84a",
                    "label": "Carousel",
                    "name": "carousel",
                    "type": "repeater",
                    "instructions": "",
                    "required": 0,
                    "conditional_logic": 0,
                    "wrapper": {
                        "width": "",
                        "class": "",
                        "id": ""
                    },
                    "collapsed": "",
                    "min": 0,
                    "max": 0,
                    "layout": "row",
                    "button_label": "",
                    "sub_fields": [
                        {
                            "key": "field_5f7e38e5081b4",
                            "label": "Icon",
                            "name": "icon",
                            "type": "image",
                            "instructions": "",
                            "required": 0,
                            "conditional_logic": 0,
                            "wrapper": {
                                "width": "",
                                "class": "",
                                "id": ""
                            },
                            "return_format": "array",
                            "preview_size": "medium",
                            "library": "all",
                            "min_width": "",
                            "min_height": "",
                            "min_size": "",
                            "max_width": "",
                            "max_height": "",
                            "max_size": "",
                            "mime_types": "",
                            "translations": "copy_once"
                        },
                        {
                            "key": "field_5f7e27b5ca84b",
                            "label": "Heading",
                            "name": "heading",
                            "type": "text",
                            "instructions": "",
                            "required": 0,
                            "conditional_logic": 0,
                            "wrapper": {
                                "width": "",
                                "class": "",
                                "id": ""
                            },
                            "default_value": "",
                            "placeholder": "",
                            "prepend": "",
                            "append": "",
                            "maxlength": "",
                            "translations": "translate"
                        },
                        {
                            "key": "field_5f7e27c8ca84c",
                            "label": "Paragraph",
                            "name": "paragraph",
                            "type": "textarea",
                            "instructions": "",
                            "required": 0,
                            "conditional_logic": 0,
                            "wrapper": {
                                "width": "",
                                "class": "",
                                "id": ""
                            },
                            "default_value": "",
                            "placeholder": "",
                            "maxlength": "",
                            "rows": "",
                            "new_lines": "",
                            "translations": "translate"
                        },
                        {
                            "key": "field_5f7e27d5ca84d",
                            "label": "Quote",
                            "name": "quote",
                            "type": "textarea",
                            "instructions": "",
                            "required": 0,
                            "conditional_logic": 0,
                            "wrapper": {
                                "width": "",
                                "class": "",
                                "id": ""
                            },
                            "default_value": "",
                            "placeholder": "",
                            "maxlength": "",
                            "rows": "",
                            "new_lines": "",
                            "translations": "translate"
                        },
                        {
                            "key": "field_5f7e27dcca84e",
                            "label": "Attribution",
                            "name": "attribution",
                            "type": "text",
                            "instructions": "",
                            "required": 0,
                            "conditional_logic": 0,
                            "wrapper": {
                                "width": "",
                                "class": "",
                                "id": ""
                            },
                            "default_value": "",
                            "placeholder": "",
                            "prepend": "",
                            "append": "",
                            "maxlength": "",
                            "translations": "translate"
                        },
                        {
                            "key": "field_5f7e2c101a24d",
                            "label": "Attribution Job Title",
                            "name": "attribution_job_title",
                            "type": "text",
                            "instructions": "",
                            "required": 0,
                            "conditional_logic": 0,
                            "wrapper": {
                                "width": "",
                                "class": "",
                                "id": ""
                            },
                            "default_value": "",
                            "placeholder": "",
                            "prepend": "",
                            "append": "",
                            "maxlength": "",
                            "translations": "translate"
                        },
                        {
                            "key": "field_5f7e27e3ca84f",
                            "label": "Link",
                            "name": "link",
                            "type": "link",
                            "instructions": "",
                            "required": 0,
                            "conditional_logic": 0,
                            "wrapper": {
                                "width": "",
                                "class": "",
                                "id": ""
                            },
                            "return_format": "array",
                            "translations": "copy_once"
                        },
                        {
                            "key": "field_5f7e27f0ca850",
                            "label": "Image",
                            "name": "image",
                            "type": "image",
                            "instructions": "",
                            "required": 0,
                            "conditional_logic": 0,
                            "wrapper": {
                                "width": "",
                                "class": "",
                                "id": ""
                            },
                            "return_format": "array",
                            "preview_size": "post-thumbnail",
                            "library": "all",
                            "min_width": "",
                            "min_height": "",
                            "min_size": "",
                            "max_width": "",
                            "max_height": "",
                            "max_size": "",
                            "mime_types": "",
                            "translations": "copy_once"
                        }
                    ]
                }
            ]
        },
        {
            "key": "field_5f2761b206224",
            "label": "Low Code Platform Essentials",
            "name": "",
            "type": "accordion",
            "instructions": "",
            "required": 0,
            "conditional_logic": 0,
            "wrapper": {
                "width": "",
                "class": "",
                "id": ""
            },
            "open": 0,
            "multi_expand": 0,
            "endpoint": 0
        },
        {
            "key": "field_5f984faa52a4a",
            "label": "Heading",
            "name": "lcg_essentials_heading",
            "type": "text",
            "instructions": "",
            "required": 0,
            "conditional_logic": 0,
            "wrapper": {
                "width": "",
                "class": "",
                "id": ""
            },
            "default_value": "Low-Code Platform Essentials",
            "placeholder": "Low-Code Platform Essentials",
            "prepend": "",
            "append": "",
            "maxlength": "",
            "translations": "translate"
        },
        {
            "key": "field_5f984fce52a4b",
            "label": "Subheading",
            "name": "lcg_essentials_subheading",
            "type": "textarea",
            "instructions": "",
            "required": 0,
            "conditional_logic": 0,
            "wrapper": {
                "width": "",
                "class": "",
                "id": ""
            },
            "default_value": "To truly leverage low-code benefits, organizations need a platform that adheres to the nine principles of low-code development and provides the ability to:",
            "placeholder": "To truly leverage low-code benefits, organizations need a platform that adheres to the nine principles of low-code development and provides the ability to:",
            "maxlength": "",
            "rows": "",
            "new_lines": "",
            "translations": "translate"
        },
        {
            "key": "field_5f984ff052a4c",
            "label": "Cards",
            "name": "lcg_essentials_cards",
            "type": "repeater",
            "instructions": "",
            "required": 0,
            "conditional_logic": 0,
            "wrapper": {
                "width": "",
                "class": "",
                "id": ""
            },
            "collapsed": "field_5f98501752a4e",
            "min": 0,
            "max": 0,
            "layout": "row",
            "button_label": "Add Card",
            "sub_fields": [
                {
                    "key": "field_5f98500752a4d",
                    "label": "Image",
                    "name": "image",
                    "type": "image",
                    "instructions": "",
                    "required": 0,
                    "conditional_logic": 0,
                    "wrapper": {
                        "width": "",
                        "class": "",
                        "id": ""
                    },
                    "return_format": "",
                    "preview_size": "post-thumbnail",
                    "library": "",
                    "min_width": "",
                    "min_height": "",
                    "min_size": "",
                    "max_width": "",
                    "max_height": "",
                    "max_size": "",
                    "mime_types": "",
                    "translations": "copy_once"
                },
                {
                    "key": "field_5f98501752a4e",
                    "label": "Heading",
                    "name": "heading",
                    "type": "text",
                    "instructions": "",
                    "required": 0,
                    "conditional_logic": 0,
                    "wrapper": {
                        "width": "",
                        "class": "",
                        "id": ""
                    },
                    "default_value": "",
                    "placeholder": "",
                    "prepend": "",
                    "append": "",
                    "maxlength": "",
                    "translations": "translate"
                },
                {
                    "key": "field_5f98501d52a4f",
                    "label": "Text",
                    "name": "text",
                    "type": "textarea",
                    "instructions": "",
                    "required": 0,
                    "conditional_logic": 0,
                    "wrapper": {
                        "width": "",
                        "class": "",
                        "id": ""
                    },
                    "default_value": "",
                    "placeholder": "",
                    "maxlength": "",
                    "rows": "",
                    "new_lines": "",
                    "translations": "translate"
                }
            ]
        },
        {
            "key": "field_5f98509a52a50",
            "label": "CTA",
            "name": "lcg_essentials_cta",
            "type": "link",
            "instructions": "",
            "required": 0,
            "conditional_logic": 0,
            "wrapper": {
                "width": "",
                "class": "",
                "id": ""
            },
            "return_format": "array",
            "translations": "copy_once"
        },
        {
            "key": "field_5f27621606226",
            "label": "Create with Low Code",
            "name": "",
            "type": "accordion",
            "instructions": "",
            "required": 0,
            "conditional_logic": 0,
            "wrapper": {
                "width": "",
                "class": "",
                "id": ""
            },
            "open": 0,
            "multi_expand": 0,
            "endpoint": 0
        },
        {
            "key": "field_5f985627cb175",
            "label": "Heading",
            "name": "lcg_create_heading",
            "type": "text",
            "instructions": "",
            "required": 0,
            "conditional_logic": 0,
            "wrapper": {
                "width": "",
                "class": "",
                "id": ""
            },
            "default_value": "Low-Code Use Cases",
            "placeholder": "Low-Code Use Cases",
            "prepend": "",
            "append": "",
            "maxlength": "",
            "translations": "translate"
        },
        {
            "key": "field_5f98566bcb17a",
            "label": "Subheading",
            "name": "lcg_create_subheading",
            "type": "textarea",
            "instructions": "",
            "required": 0,
            "conditional_logic": 0,
            "wrapper": {
                "width": "",
                "class": "",
                "id": ""
            },
            "default_value": "Your imagination is truly the limit to what you can create with low-code. But to make it easy, here are some examples of what you can build:",
            "placeholder": "Your imagination is truly the limit to what you can create with low-code. But to make it easy, here are some examples of what you can build:",
            "maxlength": "",
            "rows": "",
            "new_lines": "",
            "translations": "translate"
        },
        {
            "key": "field_5f98564fcb176",
            "label": "Cards",
            "name": "lcg_create_cards",
            "type": "repeater",
            "instructions": "",
            "required": 0,
            "conditional_logic": 0,
            "wrapper": {
                "width": "",
                "class": "",
                "id": ""
            },
            "collapsed": "field_5f98501752a4e",
            "min": 0,
            "max": 0,
            "layout": "row",
            "button_label": "Add Card",
            "sub_fields": [
                {
                    "key": "field_5f98564fcb177",
                    "label": "Image",
                    "name": "image",
                    "type": "image",
                    "instructions": "",
                    "required": 0,
                    "conditional_logic": 0,
                    "wrapper": {
                        "width": "",
                        "class": "",
                        "id": ""
                    },
                    "return_format": "array",
                    "preview_size": "post-thumbnail",
                    "library": "all",
                    "min_width": "",
                    "min_height": "",
                    "min_size": "",
                    "max_width": "",
                    "max_height": "",
                    "max_size": "",
                    "mime_types": "",
                    "translations": "copy_once"
                },
                {
                    "key": "field_5f98564fcb178",
                    "label": "Heading",
                    "name": "heading",
                    "type": "text",
                    "instructions": "",
                    "required": 0,
                    "conditional_logic": 0,
                    "wrapper": {
                        "width": "",
                        "class": "",
                        "id": ""
                    },
                    "default_value": "",
                    "placeholder": "",
                    "prepend": "",
                    "append": "",
                    "maxlength": "",
                    "translations": "translate"
                },
                {
                    "key": "field_5f98564fcb179",
                    "label": "Text",
                    "name": "text",
                    "type": "textarea",
                    "instructions": "",
                    "required": 0,
                    "conditional_logic": 0,
                    "wrapper": {
                        "width": "",
                        "class": "",
                        "id": ""
                    },
                    "default_value": "",
                    "placeholder": "",
                    "maxlength": "",
                    "rows": "",
                    "new_lines": "",
                    "translations": "translate"
                },
                {
                    "key": "field_5f986357ea320",
                    "label": "Link",
                    "name": "link",
                    "type": "link",
                    "instructions": "",
                    "required": 0,
                    "conditional_logic": 0,
                    "wrapper": {
                        "width": "",
                        "class": "",
                        "id": ""
                    },
                    "return_format": "array",
                    "translations": "copy_once"
                }
            ]
        },
        {
            "key": "field_5f98569dcb17b",
            "label": "CTA",
            "name": "lcg_create_cta",
            "type": "link",
            "instructions": "",
            "required": 0,
            "conditional_logic": 0,
            "wrapper": {
                "width": "",
                "class": "",
                "id": ""
            },
            "return_format": "array",
            "translations": "copy_once"
        },
        {
            "key": "field_5f27626906228",
            "label": "Value of Low Code",
            "name": "",
            "type": "accordion",
            "instructions": "",
            "required": 0,
            "conditional_logic": 0,
            "wrapper": {
                "width": "",
                "class": "",
                "id": ""
            },
            "open": 0,
            "multi_expand": 0,
            "endpoint": 0
        },
        {
            "key": "field_5f277616904e5",
            "label": "Background",
            "name": "value_of_low_code_background",
            "type": "image",
            "instructions": "",
            "required": 0,
            "conditional_logic": 0,
            "wrapper": {
                "width": "",
                "class": "",
                "id": ""
            },
            "return_format": "array",
            "preview_size": "post-thumbnail",
            "library": "all",
            "min_width": "",
            "min_height": "",
            "min_size": "",
            "max_width": "",
            "max_height": "",
            "max_size": "",
            "mime_types": "",
            "translations": "copy_once"
        },
        {
            "key": "field_5f278812edd68",
            "label": "Kicker",
            "name": "value_of_low_code_kicker",
            "type": "text",
            "instructions": "",
            "required": 0,
            "conditional_logic": 0,
            "wrapper": {
                "width": "",
                "class": "",
                "id": ""
            },
            "default_value": "",
            "placeholder": "",
            "prepend": "",
            "append": "",
            "maxlength": "",
            "translations": "translate"
        },
        {
            "key": "field_5f278888edd69",
            "label": "Heading",
            "name": "value_of_low_code_heading",
            "type": "text",
            "instructions": "",
            "required": 0,
            "conditional_logic": 0,
            "wrapper": {
                "width": "",
                "class": "",
                "id": ""
            },
            "default_value": "The Value of Low-Code Development",
            "placeholder": "The Value of Low-Code Development",
            "prepend": "",
            "append": "",
            "maxlength": "",
            "translations": "translate"
        },
        {
            "key": "field_5f9835ef61fe4",
            "label": "Subheading",
            "name": "value_of_low_code_subheading",
            "type": "textarea",
            "instructions": "",
            "required": 0,
            "conditional_logic": 0,
            "wrapper": {
                "width": "",
                "class": "",
                "id": ""
            },
            "default_value": "Great software solutions create immense value for the business. They can help organizations drive new revenue, enhance customer satisfaction, mitigate risks, cut costs, and more. But constantly delivering impactful solutions is hard.",
            "placeholder": "Great software solutions create immense value for the business. They can help organizations drive new revenue, enhance customer satisfaction, mitigate risks, cut costs, and more. But constantly delivering impactful solutions is hard.",
            "maxlength": "",
            "rows": "",
            "new_lines": "",
            "translations": "translate"
        },
        {
            "key": "field_5f278deec0026",
            "label": "Value of Low Code Cards",
            "name": "value_of_low_code_cards",
            "type": "repeater",
            "instructions": "",
            "required": 0,
            "conditional_logic": 0,
            "wrapper": {
                "width": "",
                "class": "",
                "id": ""
            },
            "collapsed": "",
            "min": 0,
            "max": 0,
            "layout": "table",
            "button_label": "",
            "sub_fields": [
                {
                    "key": "field_5f98362961fe5",
                    "label": "Title",
                    "name": "title",
                    "type": "text",
                    "instructions": "",
                    "required": 0,
                    "conditional_logic": 0,
                    "wrapper": {
                        "width": "",
                        "class": "",
                        "id": ""
                    },
                    "default_value": "",
                    "placeholder": "",
                    "prepend": "",
                    "append": "",
                    "maxlength": "",
                    "translations": "translate"
                },
                {
                    "key": "field_5f98363361fe6",
                    "label": "Number",
                    "name": "number",
                    "type": "text",
                    "instructions": "",
                    "required": 0,
                    "conditional_logic": 0,
                    "wrapper": {
                        "width": "",
                        "class": "",
                        "id": ""
                    },
                    "default_value": "",
                    "placeholder": "",
                    "prepend": "",
                    "append": "",
                    "maxlength": "",
                    "translations": "translate"
                },
                {
                    "key": "field_5f98363b61fe7",
                    "label": "Text",
                    "name": "text",
                    "type": "text",
                    "instructions": "",
                    "required": 0,
                    "conditional_logic": 0,
                    "wrapper": {
                        "width": "",
                        "class": "",
                        "id": ""
                    },
                    "default_value": "",
                    "placeholder": "",
                    "prepend": "",
                    "append": "",
                    "maxlength": "",
                    "translations": "translate"
                }
            ]
        },
        {
            "key": "field_5f2c57491d503",
            "label": "Value Asterix",
            "name": "value_of_low_code_asterix",
            "type": "text",
            "instructions": "",
            "required": 0,
            "conditional_logic": 0,
            "wrapper": {
                "width": "",
                "class": "",
                "id": ""
            },
            "default_value": "",
            "placeholder": "",
            "prepend": "",
            "append": "",
            "maxlength": "",
            "translations": "translate"
        },
        {
            "key": "field_5f2797b1a773f",
            "label": "Value Field Button",
            "name": "value_of_low_code_button",
            "type": "link",
            "instructions": "",
            "required": 0,
            "conditional_logic": 0,
            "wrapper": {
                "width": "",
                "class": "",
                "id": ""
            },
            "return_format": "array",
            "translations": "copy_once"
        },
        {
            "key": "field_5f2762b30622a",
            "label": "Low Code Resources",
            "name": "",
            "type": "accordion",
            "instructions": "",
            "required": 0,
            "conditional_logic": 0,
            "wrapper": {
                "width": "",
                "class": "",
                "id": ""
            },
            "open": 0,
            "multi_expand": 0,
            "endpoint": 0
        },
        {
            "key": "field_5f9865b3a4e77",
            "label": "Heading",
            "name": "lcg_resources_heading",
            "type": "text",
            "instructions": "",
            "required": 0,
            "conditional_logic": 0,
            "wrapper": {
                "width": "",
                "class": "",
                "id": ""
            },
            "default_value": "Low-Code Resources",
            "placeholder": "Low-Code Resources",
            "prepend": "",
            "append": "",
            "maxlength": "",
            "translations": "translate"
        },
        {
            "key": "field_5f984aa2f6cdc",
            "label": "Cards",
            "name": "lcg_resources_cards",
            "type": "repeater",
            "instructions": "",
            "required": 0,
            "conditional_logic": 0,
            "wrapper": {
                "width": "",
                "class": "",
                "id": ""
            },
            "collapsed": "",
            "min": 0,
            "max": 0,
            "layout": "row",
            "button_label": "Add Card",
            "sub_fields": [
                {
                    "key": "field_5f984b14f6cdd",
                    "label": "image",
                    "name": "image",
                    "type": "image",
                    "instructions": "",
                    "required": 0,
                    "conditional_logic": 0,
                    "wrapper": {
                        "width": "",
                        "class": "",
                        "id": ""
                    },
                    "return_format": "array",
                    "preview_size": "post-thumbnail",
                    "library": "all",
                    "min_width": "",
                    "min_height": "",
                    "min_size": "",
                    "max_width": "",
                    "max_height": "",
                    "max_size": "",
                    "mime_types": "",
                    "translations": "copy_once"
                },
                {
                    "key": "field_5f984b1bf6cde",
                    "label": "Heading",
                    "name": "heading",
                    "type": "text",
                    "instructions": "",
                    "required": 0,
                    "conditional_logic": 0,
                    "wrapper": {
                        "width": "",
                        "class": "",
                        "id": ""
                    },
                    "default_value": "",
                    "placeholder": "",
                    "prepend": "",
                    "append": "",
                    "maxlength": "",
                    "translations": "translate"
                },
                {
                    "key": "field_5f984b24f6cdf",
                    "label": "Text",
                    "name": "text",
                    "type": "textarea",
                    "instructions": "",
                    "required": 0,
                    "conditional_logic": 0,
                    "wrapper": {
                        "width": "",
                        "class": "",
                        "id": ""
                    },
                    "default_value": "",
                    "placeholder": "",
                    "maxlength": "",
                    "rows": "",
                    "new_lines": "",
                    "translations": "translate"
                },
                {
                    "key": "field_5f984b2df6ce0",
                    "label": "Link",
                    "name": "link",
                    "type": "link",
                    "instructions": "",
                    "required": 0,
                    "conditional_logic": 0,
                    "wrapper": {
                        "width": "",
                        "class": "",
                        "id": ""
                    },
                    "return_format": "url",
                    "translations": "copy_once"
                }
            ]
        },
        {
            "key": "field_5f2c6497ad14b",
            "label": "Videos",
            "name": "",
            "type": "accordion",
            "instructions": "",
            "required": 0,
            "conditional_logic": 0,
            "wrapper": {
                "width": "",
                "class": "",
                "id": ""
            },
            "open": 0,
            "multi_expand": 0,
            "endpoint": 0
        },
        {
            "key": "field_5f2c64c4ad14c",
            "label": "Videos",
            "name": "videos",
            "type": "group",
            "instructions": "",
            "required": 0,
            "conditional_logic": 0,
            "wrapper": {
                "width": "",
                "class": "",
                "id": ""
            },
            "layout": "block",
            "sub_fields": [
                {
                    "key": "field_5f2c64d5ad14d",
                    "label": "Headline",
                    "name": "headline",
                    "type": "text",
                    "instructions": "",
                    "required": 0,
                    "conditional_logic": 0,
                    "wrapper": {
                        "width": "",
                        "class": "",
                        "id": ""
                    },
                    "default_value": "",
                    "placeholder": "",
                    "prepend": "",
                    "append": "",
                    "maxlength": "",
                    "translations": "translate"
                },
                {
                    "key": "field_5f2c64e1ad14e",
                    "label": "The Videos",
                    "name": "the_videos",
                    "type": "repeater",
                    "instructions": "",
                    "required": 0,
                    "conditional_logic": 0,
                    "wrapper": {
                        "width": "",
                        "class": "",
                        "id": ""
                    },
                    "collapsed": "",
                    "min": 0,
                    "max": 0,
                    "layout": "table",
                    "button_label": "",
                    "sub_fields": [
                        {
                            "key": "field_5f2c64f0ad14f",
                            "label": "Icon",
                            "name": "icon",
                            "type": "image",
                            "instructions": "",
                            "required": 0,
                            "conditional_logic": 0,
                            "wrapper": {
                                "width": "",
                                "class": "",
                                "id": ""
                            },
                            "return_format": "array",
                            "preview_size": "medium",
                            "library": "all",
                            "min_width": "",
                            "min_height": "",
                            "min_size": "",
                            "max_width": "",
                            "max_height": "",
                            "max_size": "",
                            "mime_types": "",
                            "translations": "copy_once"
                        },
                        {
                            "key": "field_5f2c64f9ad150",
                            "label": "Title",
                            "name": "title",
                            "type": "text",
                            "instructions": "",
                            "required": 0,
                            "conditional_logic": 0,
                            "wrapper": {
                                "width": "",
                                "class": "",
                                "id": ""
                            },
                            "default_value": "",
                            "placeholder": "",
                            "prepend": "",
                            "append": "",
                            "maxlength": "",
                            "translations": "translate"
                        },
                        {
                            "key": "field_5f2c6503ad151",
                            "label": "Text",
                            "name": "text",
                            "type": "text",
                            "instructions": "",
                            "required": 0,
                            "conditional_logic": 0,
                            "wrapper": {
                                "width": "",
                                "class": "",
                                "id": ""
                            },
                            "default_value": "",
                            "placeholder": "",
                            "prepend": "",
                            "append": "",
                            "maxlength": "",
                            "translations": "translate"
                        },
                        {
                            "key": "field_5f2c6506ad152",
                            "label": "Vidyard",
                            "name": "vidyard",
                            "type": "text",
                            "instructions": "",
                            "required": 0,
                            "conditional_logic": 0,
                            "wrapper": {
                                "width": "",
                                "class": "",
                                "id": ""
                            },
                            "default_value": "",
                            "placeholder": "",
                            "prepend": "",
                            "append": "",
                            "maxlength": "",
                            "translations": "translate"
                        }
                    ]
                }
            ]
        }
    ],
    "location": [
        [
            {
                "param": "page_template",
                "operator": "==",
                "value": "pages\/low-code-guide.php"
            }
        ]
    ],
    "menu_order": 0,
    "position": "normal",
    "style": "default",
    "label_placement": "top",
    "instruction_placement": "label",
    "hide_on_screen": "",
    "active": true,
    "description": "",
    "modified": 1612296160
}